cirq_ft/__init__.py
cirq_ft/_version.py
cirq_ft/_version_test.py
cirq_ft/deprecation.py
cirq_ft/algos/__init__.py
cirq_ft/algos/and_gate.py
cirq_ft/algos/and_gate_test.py
cirq_ft/algos/apply_gate_to_lth_target.py
cirq_ft/algos/apply_gate_to_lth_target_test.py
cirq_ft/algos/arithmetic_gates.py
cirq_ft/algos/arithmetic_gates_test.py
cirq_ft/algos/generic_select.py
cirq_ft/algos/generic_select_test.py
cirq_ft/algos/hubbard_model.py
cirq_ft/algos/hubbard_model_test.py
cirq_ft/algos/multi_control_multi_target_pauli.py
cirq_ft/algos/multi_control_multi_target_pauli_test.py
cirq_ft/algos/prepare_uniform_superposition.py
cirq_ft/algos/prepare_uniform_superposition_test.py
cirq_ft/algos/programmable_rotation_gate_array.py
cirq_ft/algos/programmable_rotation_gate_array_test.py
cirq_ft/algos/qrom.py
cirq_ft/algos/qrom_test.py
cirq_ft/algos/qubitization_walk_operator.py
cirq_ft/algos/qubitization_walk_operator_test.py
cirq_ft/algos/reflection_using_prepare.py
cirq_ft/algos/reflection_using_prepare_test.py
cirq_ft/algos/select_and_prepare.py
cirq_ft/algos/select_swap_qrom.py
cirq_ft/algos/select_swap_qrom_test.py
cirq_ft/algos/selected_majorana_fermion.py
cirq_ft/algos/selected_majorana_fermion_test.py
cirq_ft/algos/state_preparation.py
cirq_ft/algos/state_preparation_test.py
cirq_ft/algos/swap_network.py
cirq_ft/algos/swap_network_test.py
cirq_ft/algos/unary_iteration_gate.py
cirq_ft/algos/unary_iteration_gate_test.py
cirq_ft/algos/mean_estimation/__init__.py
cirq_ft/algos/mean_estimation/arctan.py
cirq_ft/algos/mean_estimation/arctan_test.py
cirq_ft/algos/mean_estimation/complex_phase_oracle.py
cirq_ft/algos/mean_estimation/complex_phase_oracle_test.py
cirq_ft/algos/mean_estimation/mean_estimation_operator.py
cirq_ft/algos/mean_estimation/mean_estimation_operator_test.py
cirq_ft/infra/__init__.py
cirq_ft/infra/bit_tools.py
cirq_ft/infra/bit_tools_test.py
cirq_ft/infra/decompose_protocol.py
cirq_ft/infra/decompose_protocol_test.py
cirq_ft/infra/gate_with_registers.py
cirq_ft-1.4.0.dev20240510223321.dist-info/LICENSE
cirq_ft-1.4.0.dev20240510223321.dist-info/METADATA
cirq_ft-1.4.0.dev20240510223321.dist-info/WHEEL
cirq_ft-1.4.0.dev20240510223321.dist-info/top_level.txt
cirq_ft-1.4.0.dev20240510223321.dist-info/RECORD
