Metadata-Version: 2.1
Name: cirq-ft
Version: 1.4.0.dev20240510223321
Summary: A Cirq package for fault-tolerant algorithms
Home-page: http://github.com/quantumlib/cirq
Author: The Cirq Developers
Author-email: cirq-dev@googlegroups.com
License: Apache 2
Requires-Python: >=3.10.0
License-File: LICENSE
Requires-Dist: attrs
Requires-Dist: cachetools >=5.3
Requires-Dist: ipywidgets
Requires-Dist: nbconvert
Requires-Dist: nbformat
Requires-Dist: cirq-core ==1.4.0.dev20240510223321
